{
    "title": "प्रमुख रासायनिक उर्वरक | Vikaspedia - Agriculture",
    "summary": "इस भाग में प्रमुख रासायनिक उर्वरको के बारे में जानकारी दी गई है ",
    "content": "प्रमुख रासायनिक उर्वरक\nएवं उनमें पाये जाने वाले तत्वों का प्रतिशत तथा उनके गुणांक\nक्र.सं.\nउर्वरक का नाम\nतत्व प्रतिशत नत्रजन\nफास्फोरस\nपोटाश\nजिंक\n1\nयूरिया\n46\n-\n-\n-\n2\nकैल्शियम अमोनियम नाईट्रेट\n25\n-\n-\n-\n3\nएमोनियम सल्फेट\n20\n-\n-\n-\n4\nसिगिल सुपर फास्फेट\n-\n16\n-\n-\n5\nम्यूरियेट आफ पोटाश\n-\n-\n60\n-\n6\nडाइअमोनियम फास्फेट\n18\n46\n-\n-\n7\nएन.पी.के.\n15\n15\n15\n-\n8\nएन.पी.के.\n12\n32\n16\n-\n9\nएन.पी. (मिश्रण)\n20\n20\n-\n-\n10\nराक सल्फेट\n-\n18\n-\n-\n11\nजिंक सल्फेट\n-\n-\n-\n21\n12\nचिलेटेड जिंक\n-\n-\n-\n12\nप्रमुख उर्वरकों का एक किलो तत्व के लिये गुणांक (एक किलो तत्व के लिये उर्वरक मात्रा किलोग्राम)\nक्र.सं.\nउर्वरक का नाम\nनत्रजन\nफास्फोरस\nपोटाश\nजिंक\n1\nयूरिया\n22\n7\n-\n-\n2\nकैल्शियम अमोनियम नाईट्रेट\n4\n-\n-\n-\n3\nएमोनियम सल्फेट\n5\n-\n-\n-\n4\nसिंगिल सुपर फास्फेट\n-\n6.25\n-\n-\n5\nम्यूरियेट आफ पोटाश\n-\n-\n17\n-\n6\nडाइअमोनियम फास्फेट\n5.5\n22\n-\n-\n7\nएन.पी.के.\n6.7\n6.7\n6.7\n-\n8\nएन.पी.के.\n8.3\n3.8\n6.25\n-\n9\nएन.पी. (मिश्रण)\n5\n5\n-\n-\n10\nराक फास्फेट\n-\n6\n-\n-\n11\nजिंक सल्फेट\n-\n-\n-\n5\n12\nचिलेटेड जिंक\n-\n-\n-\n8\nउर्वरक विक्रय दर बिक्री कर सहित 50 किलो प्रति बोरी\nक्र.सं.\nनाम उर्वरक\nमूल्य\n1\nयूरिया 46/-\n256.61\n2\nडी.ए.पी. 18/- 46/-\n473.41\n3\nम्यूरेट आफ पोटाश (एम.ओ.पी) 60/-\n222.75\n4\nसिंगिंल सुपर फास्फेट (धूल) 16/-\n146.5\n5\nसिंगिल सुपर फास्फेट (दानेदार) 16/-\n158.5\n6\nएन.पी.के. 12-32-16/-\n427.94\nस्त्राेत : पारदर्शी किसाना सेवा याेजना, कृषि विभाग, उत्तरप्रदेश।",
    "language": "hi",
    "source": "Vikaspedia",
    "url": "https://agriculture.vikaspedia.in/viewcontent/agriculture/crop-production/91593e93094d92f92a94d93092393e93293f92f94b902-91593e-938902915941932/प्रमुख-रासायनिक-उर्वरक?lgn=hi",
    "scraped_at": "2026-07-01T17:21:10.914356",
    "word_count": 274
}