{
    "title": "लोबिया का उत्पादन एवं प्रबंधन  | Vikaspedia - Agriculture",
    "summary": "इस भाग में लोबिया के उत्पादन एवं प्रबंधन की जानकारी दी गई है। ",
    "content": "जलवायु\nलोबिया की खेती के लिए गर्म व आर्द्र जलवायु उपयुक्त है।\nतापमान\nतापमान\n240-270\nसेल्सियस के बीच ठीक रहता है। अधिक ठंडे मौसम में पौधों की बढ़वार रुक जाती है।\nमिट्टी\nसभी प्रकार की भूमि में इसकी खेती की जा सकती है। मिट्‌टी का पी-एच मान\n5.5-6.5\nउचित है। भूमि में जल निकास का उचित प्रबंध उपयुक्त\nहोना चाहिए।\nबुआई का समय\nवर्षा के मौसम के लिए इसकी बुआई जून अंत से जुलाई तक की जाती है। इसकी बुआई के लिए जनू माह उपयुक्त समय है।\nकिस्में\nलोबिया की प्रजातियां पूसा कोमल, पूसा सुकोमल, पूसा बरसाती, पूसा दो फसली, अर्का, गरिमा, काशी गौरी तथा काशी कंचन आदि हैं।\nबीज का मात्रा\nएक हैक्टर क्षेत्र में बुआई करने के लिए 15-20 कि.ग्रा. बीज पर्याप्त होता है।\nलोबिया की बौनी प्रजातियों की बुआई 45×15 सें.मी. और फैलने वाली प्रजातियों की बुआई 75×25 सें.मी. की दूरी पर करनी चाहिए।\nउर्वरक\nइसकी अच्छी फसल लेने के लिए प्रति हैक्टर 15 टन सड़ी गोबर की खाद या 8 टन नाडेप कम्पोस्ट खाद के साथ बुआई के समय 40 कि.ग्रा. नाइट्रोजन, 50 कि.ग्रा. फाॅस्फोरस एवं 50 कि.ग्रा. पोटाश/हैक्टर प्रयोग करनी चाहिए।\nस्त्रोत : खेती पत्रिका, भारतीय कृषि अनुसंधान परिषद(आईसीएआर), पूसा रोड, नई दिल्ली।",
    "language": "hi",
    "source": "Vikaspedia",
    "url": "https://agriculture.vikaspedia.in/viewcontent/agriculture/crop-production/91593f93893e92894b902-915947-93293f90f-92e94c93892e-90692793e93093f924-91594393793f-93893293e939/92e93e93993593e930-91594393793f-91593e93094d92f/जून-माह-के-कृषि-कार्य/सब्जी-वाली-फसलों-का-उत्पादन-एवं-प्रबंधन/लोबिया-का-उत्पादन-एवं-प्रबंधन?lgn=hi",
    "scraped_at": "2026-07-01T17:06:53.536071",
    "word_count": 198
}